hook_sql/__init__.py
hook_sql/_version.py
hook_sql/core.py
hook_sql/hook.py
hook_sql/manifest.py
hook_sql/py.typed
hook_sql/uss.py
hook_sql-0.3.1.dist-info/METADATA
hook_sql-0.3.1.dist-info/WHEEL
hook_sql-0.3.1.dist-info/licenses/LICENSE
hook_sql-0.3.1.dist-info/RECORD
