Metadata-Version: 2.4
Name: hook-sql
Version: 0.3.1
Summary: Add your description here
Author-email: Mattias Thalén <bitter-polders0x@icloud.com>
License-File: LICENSE
Requires-Python: <3.12,>=3.11
Requires-Dist: networkx>=3.5
Requires-Dist: sqlglot<27.29.dev0,>=27.28.0
